[
  {
    "name": "A",
    "score": 23,
    "distance": 113
  },
  {
    "name": "A",
    "score": 19,
    "distance": 137
  },
  {
    "name": "laalal",
    "score": 13,
    "distance": 195
  },
  {
    "name": "'",
    "score": 13,
    "distance": 393
  },
  {
    "name": "A",
    "score": 9,
    "distance": 93
  },
  {
    "name": "laalal",
    "score": 9,
    "distance": 72
  },
  {
    "name": "A",
    "score": 8,
    "distance": 71
  },
  {
    "name": "A",
    "score": 7,
    "distance": 41
  },
  {
    "name": "kjkjg",
    "score": 7,
    "distance": 56
  },
  {
    "name": "A",
    "score": 5,
    "distance": 10
  }
]